README.txt
setup.py
src/turboengine/__init__.py
src/turboengine/decorators.py
src/turboengine/urls.py
src/turboengine.egg-info/PKG-INFO
src/turboengine.egg-info/SOURCES.txt
src/turboengine.egg-info/dependency_links.txt
src/turboengine.egg-info/top_level.txt
src/turboengine.egg-info/zip-safe
src/turboengine/conf/__init__.py
src/turboengine/conf/global_settings.py
src/turboengine/errors/__init__.py
src/turboengine/http/__init__.py
src/turboengine/http/handler.py
src/turboengine/rest/__init__.py
src/turboengine/webservices/__init__.py
src/turboengine/webservices/application.py
src/turboengine/webservices/hacks.py