Metadata-Version: 1.0
Name: turboengine
Version: 1.0.2
Summary: Utilities for google app engine
Home-page: https://github.com/carlitux/turboengine
Author: Luis C. Cruz
Author-email: carlitos.kyo@gmail.com
License: MIT
Keywords: GAE utility
Platform: UNKNOWN
Classifier: Development Status :: 4 - Beta
Classifier: Intended Audience :: Developers
Classifier: License :: OSI Approved :: MIT License
Classifier: Topic :: Software Development :: Libraries :: Python Modules
Classifier: Topic :: Software Development :: Libraries
Classifier: Topic :: Internet
